baresquare_sdk/__init__.py
baresquare_sdk/settings.py
baresquare_sdk/aws/__init__.py
baresquare_sdk/aws/authentication.py
baresquare_sdk/aws/s3.py
baresquare_sdk/aws/ssm.py
baresquare_sdk/core/__init__.py
baresquare_sdk/core/exceptions.py
baresquare_sdk/core/http_client.py
baresquare_sdk/core/logger.py
baresquare_sdk/core/middleware/__init__.py
baresquare_sdk/core/middleware/compression.py
baresquare_sdk/core/middleware/cors.py
baresquare_sdk/core/middleware/request_info.py
baresquare_sdk/core/middleware/robots.py
baresquare_sdk/gcp/__init__.py
baresquare_sdk/gcp/authentication.py
baresquare_sdk/gcp/bigquery.py
baresquare_sdk/gcp/clients.py
baresquare_sdk/gcp/drive.py
baresquare_sdk/gcp/pagers.py
baresquare_sdk/gcp/secret_manager.py
baresquare_sdk/gcp/sheets.py
baresquare_sdk/gcp/storage.py
baresquare_sdk-1.8.5.dist-info/METADATA
baresquare_sdk-1.8.5.dist-info/WHEEL
baresquare_sdk-1.8.5.dist-info/licenses/LICENSE
baresquare_sdk-1.8.5.dist-info/RECORD
