Metadata-Version: 2.4
Name: baresquare-sdk
Version: 1.8.5
Summary: Baresquare SDK for Python - Core utilities and 3rd party integrations
License-Expression: MIT
License-File: LICENSE
Requires-Python: >=3.12
Requires-Dist: aiohttp<4.0.0,>=3.9.0
Requires-Dist: fastapi<1.0.0,>=0.115.12
Requires-Dist: pydantic-settings<3.0.0,>=2.0.0
Requires-Dist: pydantic<3.0.0,>=2.0.0
Requires-Dist: tenacity<9.0.0,>=8.2.0
Provides-Extra: aws
Requires-Dist: boto3<2.0.0,>=1.38.21; extra == 'aws'
Requires-Dist: pyjwt[crypto]<3.0.0,>=2.10.1; extra == 'aws'
Requires-Dist: requests<3.0.0,>=2.32.3; extra == 'aws'
Provides-Extra: gcp
Requires-Dist: db-dtypes>=1.4.3; extra == 'gcp'
Requires-Dist: google-api-python-client>=2.179.0; extra == 'gcp'
Requires-Dist: google-auth<3.0.0,>=2.45.0; extra == 'gcp'
Requires-Dist: google-cloud-bigquery-storage>=2.32.0; extra == 'gcp'
Requires-Dist: google-cloud-bigquery>=3.35.1; extra == 'gcp'
Requires-Dist: google-cloud-secret-manager>=2.24.0; extra == 'gcp'
Requires-Dist: google-cloud-storage>=2.10.0; extra == 'gcp'
Requires-Dist: pandas>=2.3.1; extra == 'gcp'
Provides-Extra: pretty-logs
Requires-Dist: rich>=14.1.0; extra == 'pretty-logs'
